[{"date":"2018-02-06","amount":"5400","order_number":"AF000001"},{"date":"2018-02-10","amount":"21200","order_number":"AF000002"},{"date":"2018-02-24","amount":"1300","order_number":"AF000003"},{"date":"2018-02-29","amount":"4750","order_number":"AF000004"},{"date":"2018-03-05","amount":"90","order_number":"AF000005"},{"date":"2018-03-09","amount":"3800","order_number":"AF000006"},{"date":"2018-03-15","amount":"7100","order_number":"AF000007"},{"date":"2018-03-22","amount":"13950","order_number":"AF000008"},{"date":"2018-03-26","amount":"1400","order_number":"AF000009"},{"date":"2018-04-01","amount":"17250","order_number":"AF000010"}]